[
  {
    "text": "Go straight to Edinburgh"
  },
  {
    "text": "by train"
  },
  {
    "text": "and do it in sections"
  },
  {
    "text": "You don't know where you're staying"
  },
  {
    "text": "tournament"
  },
  {
    "text": "Well they don't really mind but"
  },
  {
    "text": "Are you registered"
  },
  {
    "text": "Umm"
  },
  {
    "text": "and um tell him that we're probably gonna come in"
  },
  {
    "text": "It'd be a very good idea to um let him know"
  },
  {
    "text": "Yeah"
  },
  {
    "text": "With the extra number they'll probably be snowed under"
  },
  {
    "text": "There's also a a huge youth hostel in Edinburgh that nobody stays in in winter"
  },
  {
    "text": "Nobody stays in ah Edinburgh"
  },
  {
    "text": "At least Edinburgh was really"
  },
  {
    "text": "Raining and cold"
  },
  {
    "text": "So you'll be go to Oxford what straight away"
  },
  {
    "text": "might want to go and stay with his friends in Oxford before the tournament"
  },
  {
    "text": "Yeah"
  },
  {
    "text": "I've got the really good maps yeah"
  },
  {
    "text": "Stratford's not far from it"
  },
  {
    "text": "There's um and of course Reading's not far either"
  },
  {
    "text": "What's in Reading"
  },
  {
    "text": "Banbury Cross"
  },
  {
    "text": "Where have I heard of that"
  },
  {
    "text": "Ride a cock horse"
  },
  {
    "text": "That's right"
  },
  {
    "text": "Banbury Cross"
  },
  {
    "text": "To see a fine lady um"
  },
  {
    "text": "Well you want"
  },
  {
    "text": "And we're going to go to Fishbourne"
  },
  {
    "text": "Oh Fishbourne's nice"
  },
  {
    "text": "from uh history and stuff"
  },
  {
    "text": "If you get good weather"
  },
  {
    "text": "Yeah"
  },
  {
    "text": "That was the winter of nineteen sixty-three"
  },
  {
    "text": "every day"
  },
  {
    "text": "January January nineteen sixty-two it was"
  },
  {
    "text": "Sorry January nineteen sixty-three"
  },
  {
    "text": "Exactly thirty years ago"
  },
  {
    "text": "Walk along and there'd be dead pigeons it on the on the sidewalk frozen"
  },
  {
    "text": "That's right"
  },
  {
    "text": "Amazing"
  },
  {
    "text": "That was the year before though"
  },
  {
    "text": "before that smokeless fuel thing really took over in England"
  },
  {
    "text": "The smog"
  },
  {
    "text": "You couldn't see you could not see your hand you could not put you could not see your hands at arm's length in front of your face"
  },
  {
    "text": "Gosh"
  },
  {
    "text": "If you put a handkerchief across your face in about half an hour it was it was totally black on the outside from where you were breathing through"
  },
  {
    "text": "Oh I've got to be there at eleven o'clock"
  },
  {
    "text": "Got to sign this register"
  },
  {
    "text": "Yeah"
  },
  {
    "text": "They must have trouble getting everybody to sign wouldn't they"
  },
  {
    "text": "Mm well what what she said is there's a default um like um default assessment which is fifty-fifty and everybody er and if you only have to you only have to sign it if it's seventy-five twenty-five but she wants everyone to sign it to make sure because apparently it's really complicated having different systems of assessment for the same course and she has to get the administration worked out for it"
  },
  {
    "text": "Do they"
  },
  {
    "text": "Seventy-five"
  },
  {
    "text": "Seventy-five for the exam and twenty-five for the essays because a lot of people have done really badly in the essays and they think they're gonna do better in the exam"
  },
  {
    "text": "Do you think that's likely"
  },
  {
    "text": "See the thing is"
  },
  {
    "text": "but"
  },
  {
    "text": "Yeah"
  },
  {
    "text": "You you would expect some kind of um comparison favourable comparison"
  },
  {
    "text": "Yes"
  },
  {
    "text": "exactly"
  },
  {
    "text": "And and the exam is a prepared question"
  },
  {
    "text": "That's right we've had effectively we've had an assessment on each of those three"
  },
  {
    "text": "Right"
  },
  {
    "text": "So it should be quite interesting"
  },
  {
    "text": "Less than fifty"
  },
  {
    "text": "tell"
  },
  {
    "text": "A lot of those are hatching on the plants in the garden actually"
  },
  {
    "text": "It was flying around inside the car"
  },
  {
    "text": "I just couldn't get it to go out"
  },
  {
    "text": "Bees in cars cause accidents"
  },
  {
    "text": "completely literature"
  },
  {
    "text": "Right"
  },
  {
    "text": "So they don't know about the um,"
  },
  {
    "text": "Oh so that's"
  },
  {
    "text": "Know that the um"
  },
  {
    "text": "The the linguistic people"
  },
  {
    "text": "might be useful"
  },
  {
    "text": "Do you know enough about stories"
  },
  {
    "text": "Mm"
  },
  {
    "text": "to write about them"
  },
  {
    "text": "Like I've got my eight credit points of second year literature which is all they have"
  },
  {
    "text": "Do you count that as a sequence in in literature"
  },
  {
    "text": "if I want to"
  },
  {
    "text": "So how many what's your sequence of literature then"
  },
  {
    "text": "So it would only count if I was doing a coherent major in literature which would mean I'd have to have three subjects in literature at third year level"
  },
  {
    "text": "So if you want to do a sequence in literature what else would you have to do"
  },
  {
    "text": "someone said that you can't add subjects to your arts degree after you've graduated so um if I choose to graduate"
  },
  {
    "text": "You're not going to graduate till you've done your law"
  }
]